Metadata-Version: 1.0
Name: Distribution-Ritika
Version: 0.17
Summary: Gaussian and Binomial distributions
Home-page: UNKNOWN
Author: Ritika_Gupta
Author-email: UNKNOWN
License: UNKNOWN
Platform: UNKNOWN
